modi_helper/__init__.py
modi_helper/defaults.py
modi_helper/cli/__init__.py
modi_helper/cli/environment_delete.py
modi_helper/cli/environment_new.py
modi_helper/cli/environments_list.py
modi_helper/cli/environments_load.py
modi_helper/cli/job_submit.py
modi_helper/cli/return_codes.py
modi_helper/environment/__init__.py
modi_helper/environment/create.py
modi_helper/environment/delete.py
modi_helper/environment/initialize.py
modi_helper/environment/list.py
modi_helper/job/__init__.py
modi_helper/job/initialize.py
modi_helper/job/run.py
modi_helper/templates/__init__.py
modi_helper/templates/container_wrap.j2
modi_helper/templates/regular.j2
modi_helper/utils/__init__.py
modi_helper/utils/io.py
modi_helper/utils/job.py
modi_helper-0.0.1a4.dist-info/METADATA
modi_helper-0.0.1a4.dist-info/WHEEL
modi_helper-0.0.1a4.dist-info/entry_points.txt
modi_helper-0.0.1a4.dist-info/top_level.txt
modi_helper-0.0.1a4.dist-info/RECORD
