Metadata-Version: 2.1
Name: modi-helper
Version: 0.0.1a4
Summary: A set of scripts and tools to help configure a MODI environment.
Home-page: https://github.com/ucphhpc/modi-helper-scripts
Author: Rasmus Munk
Author-email: munk1@live.dk
Classifier: Intended Audience :: Developers
Classifier: Intended Audience :: System Administrators
Classifier: Programming Language :: Python :: 3.8
Classifier: Programming Language :: Python :: 3.9
Classifier: Programming Language :: Python :: 3.10
Classifier: Programming Language :: Python :: 3.11
Classifier: Programming Language :: Python :: 3.12
Requires-Dist: click==8.1.0
Requires-Dist: jinja2
Provides-Extra: dev
Requires-Dist: black>=24.3.0; extra == "dev"
Requires-Dist: flake8>=6.1.0; extra == "dev"
Requires-Dist: black[jupyter]>=0.3.0; extra == "dev"
